spacecan/__init__.py
spacecan/controller.py
spacecan/responder.py
spacecan/primitives/__init__.py
spacecan/primitives/can_frame.py
spacecan/primitives/heartbeat.py
spacecan/primitives/network.py
spacecan/primitives/packet.py
spacecan/primitives/sync.py
spacecan/primitives/timer.py
spacecan/services/__init__.py
spacecan/services/core.py
spacecan/services/function.py
spacecan/services/housekeeping.py
spacecan/services/parameter.py
spacecan/services/request.py
spacecan/services/service_packet.py
spacecan/services/test.py
spacecan/transport/__init__.py
spacecan/transport/base.py
spacecan/transport/socketcan.py
spacecan-5.2.0.dist-info/licenses/LICENSE.txt
spacecan-5.2.0.dist-info/METADATA
spacecan-5.2.0.dist-info/WHEEL
spacecan-5.2.0.dist-info/top_level.txt
spacecan-5.2.0.dist-info/RECORD
