Metadata-Version: 2.4
Name: spacecan
Version: 5.2.0
Summary: Python implementation of SpaceCAN protocol
Author-email: LibreCube <info@librecube.org>
License: MIT License
License-File: LICENSE.txt
Requires-Dist: python-can
Dynamic: license-file
